[
  {"time": "2026-03-05T12:43:00Z", "action": "heartbeat_check", "status": "healthy", "notes": "系统运行正常，转世系统已关闭，等待用户指示"},
  {"time": "2026-03-05T11:24:00Z", "action": "heartbeat_check", "status": "healthy", "notes": "第76世刚完成，下一世任务: 告警历史展示"},
  {"time": "2026-03-05T11:10:00Z", "action": "heartbeat_check", "status": "healthy", "notes": "系统运行正常"}
],{"timestamp": "2026-03-05T14:38:00Z", "type": "heartbeat", "action": "system_check", "result": "healthy", "load": 0.36, "memory_percent": 14, "note": "运行4天20小时，所有服务正常"}
,{"timestamp": "2026-03-05T15:11:53Z", "type": "heartbeat", "action": "system_check", "result": "healthy", "load": 0.71, "memory_percent": 15, "note": "运行4天21小时，所有服务正常"}]
