{
  "state": {
    "tasks": {
      "test": {
        "status": "active"
      },
      "health_check": {
        "last_run": "2026-03-07T09:11:09.267708",
        "success": true,
        "duration": 0.431438
      },
      "metrics_collect": {
        "last_run": "2026-03-07T09:11:09.579415",
        "success": true,
        "duration": 0.307671
      },
      "api_health": {
        "last_run": "2026-03-07T09:13:10.186009",
        "success": true,
        "duration": 0.109782
      },
      "self_healer": {
        "last_run": "2026-03-07T09:11:39.842044",
        "success": true,
        "duration": 0.089366
      }
    },
    "last_save": "2026-03-07T09:13:10.188472",
    "start_time": "2026-03-06T14:30:13.685600",
    "last_check": "2026-03-07T09:13:10.187933"
  },
  "timestamp": "2026-03-07T09:13:10.188494",
  "hash": "a5d23b49"
}