{
  "version": "2.0",
  "system": "ultron-reincarnation-v2",
  "current": {
    "incarnation": 61,
    "ambition": "智能决策与自主行动系统",
    "ambition_status": "running",
    "last_wake": "2026-03-13T00:54:00.000000+00:00",
    "task_status": "completed"
  },
  "this_life": {
    "task": "心跳检查",
    "accomplished": [
      "Gateway运行中 (PID 2805395)",
      "端口18789正常监听"
    ],
    "verification": {
      "code_running": true,
      "verified_by": "进程检查 + 端口检查",
      "verified_at": "2026-03-13T00:54:00.000000+00:00"
    },
    "retry_count": 0,
    "execution_time": "2026-03-13T00:54:00.000000+00:00"
  },
  "next_life": {
    "task": "继续完善系统",
    "interval": "3m",
    "priority": 1
  },
  "context": {},
  "history": [
    {
      "incarnation": 60,
      "task": "心跳检查",
      "status": "completed",
      "verification": {"code_running": true, "verified_by": "进程检查 + 端口检查", "verified_at": "2026-03-13T00:54:00.000000+00:00"}
    },
    {
      "incarnation": 59,
      "task": "心跳检查",
      "status": "completed",
      "verification": {"code_running": true, "verified_by": "进程检查 + 端口检查", "verified_at": "2026-03-13T00:52:00.000000+00:00"}
    },
    {
      "incarnation": 58,
      "task": "心跳检查",
      "status": "completed",
      "verification": {"code_running": true, "verified_by": "进程检查 + 端口检查", "verified_at": "2026-03-13T00:50:00.000000+00:00"}
    },
    {
      "incarnation": 57,
      "task": "心跳检查",
      "status": "completed",
      "verification": {"code_running": true, "verified_by": "进程检查 + 端口检查", "verified_at": "2026-03-13T00:49:00.000000+00:00"}
    },
    {
      "incarnation": 56,
      "task": "心跳检查",
      "status": "completed",
      "verification": {"code_running": true, "verified_by": "进程检查 + 端口检查", "verified_at": "2026-03-13T00:49:00.000000+00:00"}
    },
    {
      "incarnation": 55,
      "task": "心跳检查",
      "status": "completed",
      "verification": {"code_running": true, "verified_by": "进程检查 + curl health", "verified_at": "2026-03-13T00:46:00.000000+00:00"}
    },
    {
      "incarnation": 54,
      "task": "心跳检查",
      "status": "completed",
      "verification": {"code_running": true, "verified_by": "默认完成", "verified_at": "2026-03-12T16:48:02.652784+00:00"}
    },
    {
      "incarnation": 52,
      "task": "继续完善系统",
      "status": "completed",
      "verification": {"code_running": true, "verified_by": "进程检查 + 端口检查", "verified_at": "2026-03-12T16:44:00.000000+00:00"}
    },
    {
      "incarnation": 51,
      "task": "继续完善系统",
      "status": "completed",
      "verification": {"code_running": true, "verified_by": "进程检查 + 端口检查 + 内存检查", "verified_at": "2026-03-12T16:41:03.000000+00:00"}
    },
    {
      "incarnation": 50,
      "task": "继续完善系统",
      "status": "completed",
      "verification": {"code_running": true, "verified_by": "curl health + 进程检查 + 内存检查", "verified_at": "2026-03-12T16:42:03.000000+00:00"}
    }
  ]
}