[
  {
    "timestamp": "2026-03-07T10:16:34.102147",
    "system": {
      "load": {
        "1m": 2.26,
        "5m": 1.57,
        "15m": 1.5
      },
      "memory": {
        "total": 7266,
        "available": 4560,
        "used": 2706,
        "percent": 37.2
      },
      "gateway_processes": 43
    },
    "services": {
      "gateway": "healthy",
      "status_panel": "error_000",
      "health_api": "healthy",
      "dashboard": "error_000"
    },
    "network": {
      "connections": 8
    }
  },
  {
    "timestamp": "2026-03-07T10:21:35.626431",
    "system": {
      "load": {
        "1m": 1.35,
        "5m": 1.58,
        "15m": 1.53
      },
      "memory": {
        "total": 7266,
        "available": 5058,
        "used": 2208,
        "percent": 30.4
      },
      "gateway_processes": 40
    },
    "services": {
      "gateway": "healthy",
      "status_panel": "error_000",
      "health_api": "healthy",
      "dashboard": "error_000"
    },
    "network": {
      "connections": 5
    }
  },
  {
    "timestamp": "2026-03-07T10:26:37.373991",
    "system": {
      "load": {
        "1m": 1.31,
        "5m": 1.4,
        "15m": 1.46
      },
      "memory": {
        "total": 7266,
        "available": 4720,
        "used": 2546,
        "percent": 35.0
      },
      "gateway_processes": 43
    },
    "services": {
      "gateway": "healthy",
      "status_panel": "error_000",
      "health_api": "healthy",
      "dashboard": "error_000"
    },
    "network": {
      "connections": 4
    }
  },
  {
    "timestamp": "2026-03-07T10:31:39.163899",
    "system": {
      "load": {
        "1m": 1.09,
        "5m": 1.24,
        "15m": 1.38
      },
      "memory": {
        "total": 7266,
        "available": 5063,
        "used": 2203,
        "percent": 30.3
      },
      "gateway_processes": 40
    },
    "services": {
      "gateway": "healthy",
      "status_panel": "error_000",
      "health_api": "healthy",
      "dashboard": "error_000"
    },
    "network": {
      "connections": 8
    }
  },
  {
    "timestamp": "2026-03-07T10:36:40.880417",
    "system": {
      "load": {
        "1m": 1.18,
        "5m": 1.2,
        "15m": 1.31
      },
      "memory": {
        "total": 7266,
        "available": 5057,
        "used": 2209,
        "percent": 30.4
      },
      "gateway_processes": 40
    },
    "services": {
      "gateway": "healthy",
      "status_panel": "error_000",
      "health_api": "healthy",
      "dashboard": "error_000"
    },
    "network": {
      "connections": 6
    }
  },
  {
    "timestamp": "2026-03-07T10:41:42.341210",
    "system": {
      "load": {
        "1m": 1.29,
        "5m": 1.29,
        "15m": 1.32
      },
      "memory": {
        "total": 7266,
        "available": 5055,
        "used": 2211,
        "percent": 30.4
      },
      "gateway_processes": 40
    },
    "services": {
      "gateway": "healthy",
      "status_panel": "error_000",
      "health_api": "healthy",
      "dashboard": "error_000"
    },
    "network": {
      "connections": 9
    }
  },
  {
    "timestamp": "2026-03-07T10:46:43.923942",
    "system": {
      "load": {
        "1m": 1.29,
        "5m": 1.24,
        "15m": 1.29
      },
      "memory": {
        "total": 7266,
        "available": 4748,
        "used": 2518,
        "percent": 34.7
      },
      "gateway_processes": 42
    },
    "services": {
      "gateway": "healthy",
      "status_panel": "error_000",
      "health_api": "healthy",
      "dashboard": "error_000"
    },
    "network": {
      "connections": 6
    }
  },
  {
    "timestamp": "2026-03-07T10:51:45.733479",
    "system": {
      "load": {
        "1m": 1.43,
        "5m": 1.14,
        "15m": 1.21
      },
      "memory": {
        "total": 7266,
        "available": 5094,
        "used": 2172,
        "percent": 29.9
      },
      "gateway_processes": 40
    },
    "services": {
      "gateway": "healthy",
      "status_panel": "error_000",
      "health_api": "healthy",
      "dashboard": "error_000"
    },
    "network": {
      "connections": 6
    }
  },
  {
    "timestamp": "2026-03-07T10:56:47.471072",
    "system": {
      "load": {
        "1m": 0.57,
        "5m": 0.88,
        "15m": 1.08
      },
      "memory": {
        "total": 7266,
        "available": 5031,
        "used": 2235,
        "percent": 30.8
      },
      "gateway_processes": 40
    },
    "services": {
      "gateway": "healthy",
      "status_panel": "error_000",
      "health_api": "healthy",
      "dashboard": "error_000"
    },
    "network": {
      "connections": 8
    }
  },
  {
    "timestamp": "2026-03-07T11:01:49.251785",
    "system": {
      "load": {
        "1m": 0.59,
        "5m": 0.91,
        "15m": 1.05
      },
      "memory": {
        "total": 7266,
        "available": 5205,
        "used": 2061,
        "percent": 28.4
      },
      "gateway_processes": 43
    },
    "services": {
      "gateway": "healthy",
      "status_panel": "error_000",
      "health_api": "healthy",
      "dashboard": "error_000"
    },
    "network": {
      "connections": 6
    }
  },
  {
    "timestamp": "2026-03-07T11:06:51.523408",
    "system": {
      "load": {
        "1m": 1.34,
        "5m": 1.31,
        "15m": 1.19
      },
      "memory": {
        "total": 7266,
        "available": 5245,
        "used": 2021,
        "percent": 27.8
      },
      "gateway_processes": 40
    },
    "services": {
      "gateway": "healthy",
      "status_panel": "error_000",
      "health_api": "healthy",
      "dashboard": "error_000"
    },
    "network": {
      "connections": 7
    }
  },
  {
    "timestamp": "2026-03-07T11:11:53.222260",
    "system": {
      "load": {
        "1m": 0.86,
        "5m": 1.1,
        "15m": 1.12
      },
      "memory": {
        "total": 7266,
        "available": 4491,
        "used": 2775,
        "percent": 38.2
      },
      "gateway_processes": 40
    },
    "services": {
      "gateway": "healthy",
      "status_panel": "error_000",
      "health_api": "healthy",
      "dashboard": "error_000"
    },
    "network": {
      "connections": 7
    }
  },
  {
    "timestamp": "2026-03-07T11:16:54.911284",
    "system": {
      "load": {
        "1m": 1.15,
        "5m": 1.08,
        "15m": 1.1
      },
      "memory": {
        "total": 7266,
        "available": 5251,
        "used": 2015,
        "percent": 27.7
      },
      "gateway_processes": 40
    },
    "services": {
      "gateway": "healthy",
      "status_panel": "error_000",
      "health_api": "healthy",
      "dashboard": "error_000"
    },
    "network": {
      "connections": 6
    }
  },
  {
    "timestamp": "2026-03-07T11:21:56.602546",
    "system": {
      "load": {
        "1m": 0.58,
        "5m": 0.89,
        "15m": 1.01
      },
      "memory": {
        "total": 7266,
        "available": 5305,
        "used": 1961,
        "percent": 27.0
      },
      "gateway_processes": 40
    },
    "services": {
      "gateway": "healthy",
      "status_panel": "error_000",
      "health_api": "healthy",
      "dashboard": "error_000"
    },
    "network": {
      "connections": 6
    }
  },
  {
    "timestamp": "2026-03-07T11:26:58.486416",
    "system": {
      "load": {
        "1m": 0.96,
        "5m": 1.1,
        "15m": 1.09
      },
      "memory": {
        "total": 7266,
        "available": 4472,
        "used": 2794,
        "percent": 38.5
      },
      "gateway_processes": 40
    },
    "services": {
      "gateway": "healthy",
      "status_panel": "error_000",
      "health_api": "healthy",
      "dashboard": "error_000"
    },
    "network": {
      "connections": 7
    }
  },
  {
    "timestamp": "2026-03-07T11:32:00.407135",
    "system": {
      "load": {
        "1m": 0.55,
        "5m": 0.98,
        "15m": 1.06
      },
      "memory": {
        "total": 7266,
        "available": 4724,
        "used": 2542,
        "percent": 35.0
      },
      "gateway_processes": 42
    },
    "services": {
      "gateway": "healthy",
      "status_panel": "error_000",
      "health_api": "healthy",
      "dashboard": "error_000"
    },
    "network": {
      "connections": 6
    }
  },
  {
    "timestamp": "2026-03-07T11:37:02.176981",
    "system": {
      "load": {
        "1m": 1.03,
        "5m": 1.17,
        "15m": 1.12
      },
      "memory": {
        "total": 7266,
        "available": 4484,
        "used": 2782,
        "percent": 38.3
      },
      "gateway_processes": 40
    },
    "services": {
      "gateway": "healthy",
      "status_panel": "error_000",
      "health_api": "healthy",
      "dashboard": "error_000"
    },
    "network": {
      "connections": 9
    }
  },
  {
    "timestamp": "2026-03-07T11:42:03.705543",
    "system": {
      "load": {
        "1m": 1.16,
        "5m": 1.17,
        "15m": 1.12
      },
      "memory": {
        "total": 7266,
        "available": 4524,
        "used": 2742,
        "percent": 37.7
      },
      "gateway_processes": 40
    },
    "services": {
      "gateway": "healthy",
      "status_panel": "error_000",
      "health_api": "healthy",
      "dashboard": "error_000"
    },
    "network": {
      "connections": 6
    }
  },
  {
    "timestamp": "2026-03-07T11:47:05.190411",
    "system": {
      "load": {
        "1m": 0.42,
        "5m": 0.91,
        "15m": 1.04
      },
      "memory": {
        "total": 7266,
        "available": 5020,
        "used": 2246,
        "percent": 30.9
      },
      "gateway_processes": 40
    },
    "services": {
      "gateway": "healthy",
      "status_panel": "error_000",
      "health_api": "healthy",
      "dashboard": "error_000"
    },
    "network": {
      "connections": 5
    }
  },
  {
    "timestamp": "2026-03-07T11:52:06.716741",
    "system": {
      "load": {
        "1m": 0.72,
        "5m": 1.04,
        "15m": 1.07
      },
      "memory": {
        "total": 7266,
        "available": 4884,
        "used": 2382,
        "percent": 32.8
      },
      "gateway_processes": 40
    },
    "services": {
      "gateway": "healthy",
      "status_panel": "error_000",
      "health_api": "healthy",
      "dashboard": "error_000"
    },
    "network": {
      "connections": 7
    }
  },
  {
    "timestamp": "2026-03-07T11:57:08.328556",
    "system": {
      "load": {
        "1m": 0.78,
        "5m": 1.03,
        "15m": 1.07
      },
      "memory": {
        "total": 7266,
        "available": 5305,
        "used": 1961,
        "percent": 27.0
      },
      "gateway_processes": 40
    },
    "services": {
      "gateway": "healthy",
      "status_panel": "error_000",
      "health_api": "healthy",
      "dashboard": "error_000"
    },
    "network": {
      "connections": 6
    }
  },
  {
    "timestamp": "2026-03-07T12:02:09.801541",
    "system": {
      "load": {
        "1m": 0.53,
        "5m": 0.7,
        "15m": 0.91
      },
      "memory": {
        "total": 7266,
        "available": 5320,
        "used": 1946,
        "percent": 26.8
      },
      "gateway_processes": 40
    },
    "services": {
      "gateway": "healthy",
      "status_panel": "error_000",
      "health_api": "healthy",
      "dashboard": "error_000"
    },
    "network": {
      "connections": 6
    }
  },
  {
    "timestamp": "2026-03-07T12:07:11.563486",
    "system": {
      "load": {
        "1m": 0.99,
        "5m": 0.96,
        "15m": 0.97
      },
      "memory": {
        "total": 7266,
        "available": 5270,
        "used": 1996,
        "percent": 27.5
      },
      "gateway_processes": 40
    },
    "services": {
      "gateway": "healthy",
      "status_panel": "error_000",
      "health_api": "healthy",
      "dashboard": "error_000"
    },
    "network": {
      "connections": 7
    }
  },
  {
    "timestamp": "2026-03-07T12:12:13.219286",
    "system": {
      "load": {
        "1m": 1.61,
        "5m": 1.2,
        "15m": 1.05
      },
      "memory": {
        "total": 7266,
        "available": 4956,
        "used": 2310,
        "percent": 31.8
      },
      "gateway_processes": 40
    },
    "services": {
      "gateway": "healthy",
      "status_panel": "error_000",
      "health_api": "healthy",
      "dashboard": "error_000"
    },
    "network": {
      "connections": 5
    }
  },
  {
    "timestamp": "2026-03-07T12:17:15.425700",
    "system": {
      "load": {
        "1m": 1.49,
        "5m": 1.3,
        "15m": 1.11
      },
      "memory": {
        "total": 7266,
        "available": 5040,
        "used": 2226,
        "percent": 30.6
      },
      "gateway_processes": 40
    },
    "services": {
      "gateway": "healthy",
      "status_panel": "error_000",
      "health_api": "healthy",
      "dashboard": "error_000"
    },
    "network": {
      "connections": 5
    }
  },
  {
    "timestamp": "2026-03-07T12:22:17.553564",
    "system": {
      "load": {
        "1m": 0.68,
        "5m": 0.97,
        "15m": 1.02
      },
      "memory": {
        "total": 7266,
        "available": 5191,
        "used": 2075,
        "percent": 28.6
      },
      "gateway_processes": 40
    },
    "services": {
      "gateway": "healthy",
      "status_panel": "error_000",
      "health_api": "healthy",
      "dashboard": "error_000"
    },
    "network": {
      "connections": 8
    }
  },
  {
    "timestamp": "2026-03-07T12:27:19.631724",
    "system": {
      "load": {
        "1m": 1.4,
        "5m": 1.15,
        "15m": 1.07
      },
      "memory": {
        "total": 7266,
        "available": 4340,
        "used": 2926,
        "percent": 40.3
      },
      "gateway_processes": 49
    },
    "services": {
      "gateway": "healthy",
      "status_panel": "error_000",
      "health_api": "healthy",
      "dashboard": "error_000"
    },
    "network": {
      "connections": 7
    }
  },
  {
    "timestamp": "2026-03-07T12:32:22.430753",
    "system": {
      "load": {
        "1m": 1.03,
        "5m": 2.14,
        "15m": 1.65
      },
      "memory": {
        "total": 7266,
        "available": 5399,
        "used": 1867,
        "percent": 25.7
      },
      "gateway_processes": 40
    },
    "services": {
      "gateway": "healthy",
      "status_panel": "error_000",
      "health_api": "healthy",
      "dashboard": "error_000"
    },
    "network": {
      "connections": 6
    }
  },
  {
    "timestamp": "2026-03-07T12:37:24.006063",
    "system": {
      "load": {
        "1m": 1.26,
        "5m": 1.48,
        "15m": 1.47
      },
      "memory": {
        "total": 7266,
        "available": 4793,
        "used": 2473,
        "percent": 34.0
      },
      "gateway_processes": 40
    },
    "services": {
      "gateway": "healthy",
      "status_panel": "error_000",
      "health_api": "healthy",
      "dashboard": "error_000"
    },
    "network": {
      "connections": 7
    }
  },
  {
    "timestamp": "2026-03-07T12:42:25.564378",
    "system": {
      "load": {
        "1m": 1.52,
        "5m": 1.72,
        "15m": 1.58
      },
      "memory": {
        "total": 7266,
        "available": 4746,
        "used": 2520,
        "percent": 34.7
      },
      "gateway_processes": 40
    },
    "services": {
      "gateway": "healthy",
      "status_panel": "error_000",
      "health_api": "healthy",
      "dashboard": "error_000"
    },
    "network": {
      "connections": 5
    }
  },
  {
    "timestamp": "2026-03-07T12:47:27.379406",
    "system": {
      "load": {
        "1m": 1.61,
        "5m": 1.75,
        "15m": 1.63
      },
      "memory": {
        "total": 7266,
        "available": 4475,
        "used": 2791,
        "percent": 38.4
      },
      "gateway_processes": 43
    },
    "services": {
      "gateway": "healthy",
      "status_panel": "error_000",
      "health_api": "healthy",
      "dashboard": "error_000"
    },
    "network": {
      "connections": 8
    }
  },
  {
    "timestamp": "2026-03-07T12:52:29.033624",
    "system": {
      "load": {
        "1m": 1.48,
        "5m": 1.46,
        "15m": 1.53
      },
      "memory": {
        "total": 7266,
        "available": 5055,
        "used": 2211,
        "percent": 30.4
      },
      "gateway_processes": 40
    },
    "services": {
      "gateway": "healthy",
      "status_panel": "error_000",
      "health_api": "healthy",
      "dashboard": "error_000"
    },
    "network": {
      "connections": 6
    }
  },
  {
    "timestamp": "2026-03-07T12:57:31.038000",
    "system": {
      "load": {
        "1m": 2.57,
        "5m": 1.9,
        "15m": 1.68
      },
      "memory": {
        "total": 7266,
        "available": 4184,
        "used": 3082,
        "percent": 42.4
      },
      "gateway_processes": 45
    },
    "services": {
      "gateway": "healthy",
      "status_panel": "error_000",
      "health_api": "healthy",
      "dashboard": "error_000"
    },
    "network": {
      "connections": 6
    }
  },
  {
    "timestamp": "2026-03-07T13:02:32.801197",
    "system": {
      "load": {
        "1m": 0.88,
        "5m": 1.38,
        "15m": 1.51
      },
      "memory": {
        "total": 7266,
        "available": 5333,
        "used": 1933,
        "percent": 26.6
      },
      "gateway_processes": 40
    },
    "services": {
      "gateway": "healthy",
      "status_panel": "error_000",
      "health_api": "healthy",
      "dashboard": "error_000"
    },
    "network": {
      "connections": 8
    }
  },
  {
    "timestamp": "2026-03-07T13:07:34.731595",
    "system": {
      "load": {
        "1m": 1.32,
        "5m": 1.55,
        "15m": 1.58
      },
      "memory": {
        "total": 7266,
        "available": 4439,
        "used": 2827,
        "percent": 38.9
      },
      "gateway_processes": 42
    },
    "services": {
      "gateway": "healthy",
      "status_panel": "error_000",
      "health_api": "healthy",
      "dashboard": "error_000"
    },
    "network": {
      "connections": 7
    }
  },
  {
    "timestamp": "2026-03-07T13:12:36.567971",
    "system": {
      "load": {
        "1m": 2.56,
        "5m": 2.11,
        "15m": 1.79
      },
      "memory": {
        "total": 7266,
        "available": 4337,
        "used": 2929,
        "percent": 40.3
      },
      "gateway_processes": 43
    },
    "services": {
      "gateway": "healthy",
      "status_panel": "error_000",
      "health_api": "healthy",
      "dashboard": "error_000"
    },
    "network": {
      "connections": 6
    }
  },
  {
    "timestamp": "2026-03-07T13:17:38.249262",
    "system": {
      "load": {
        "1m": 1.76,
        "5m": 1.82,
        "15m": 1.74
      },
      "memory": {
        "total": 7266,
        "available": 5002,
        "used": 2264,
        "percent": 31.2
      },
      "gateway_processes": 43
    },
    "services": {
      "gateway": "healthy",
      "status_panel": "error_000",
      "health_api": "healthy",
      "dashboard": "error_000"
    },
    "network": {
      "connections": 7
    }
  },
  {
    "timestamp": "2026-03-07T13:22:39.969657",
    "system": {
      "load": {
        "1m": 1.59,
        "5m": 1.66,
        "15m": 1.69
      },
      "memory": {
        "total": 7266,
        "available": 5032,
        "used": 2234,
        "percent": 30.7
      },
      "gateway_processes": 40
    },
    "services": {
      "gateway": "healthy",
      "status_panel": "error_000",
      "health_api": "healthy",
      "dashboard": "error_000"
    },
    "network": {
      "connections": 6
    }
  },
  {
    "timestamp": "2026-03-07T13:27:41.546823",
    "system": {
      "load": {
        "1m": 1.52,
        "5m": 1.6,
        "15m": 1.65
      },
      "memory": {
        "total": 7266,
        "available": 4565,
        "used": 2701,
        "percent": 37.2
      },
      "gateway_processes": 40
    },
    "services": {
      "gateway": "healthy",
      "status_panel": "error_000",
      "health_api": "healthy",
      "dashboard": "error_000"
    },
    "network": {
      "connections": 8
    }
  },
  {
    "timestamp": "2026-03-07T13:32:43.220966",
    "system": {
      "load": {
        "1m": 2.0,
        "5m": 1.54,
        "15m": 1.58
      },
      "memory": {
        "total": 7266,
        "available": 4287,
        "used": 2979,
        "percent": 41.0
      },
      "gateway_processes": 43
    },
    "services": {
      "gateway": "healthy",
      "status_panel": "error_000",
      "health_api": "healthy",
      "dashboard": "error_000"
    },
    "network": {
      "connections": 5
    }
  },
  {
    "timestamp": "2026-03-07T13:37:45.769706",
    "system": {
      "load": {
        "1m": 1.44,
        "5m": 1.42,
        "15m": 1.53
      },
      "memory": {
        "total": 7266,
        "available": 4537,
        "used": 2729,
        "percent": 37.6
      },
      "gateway_processes": 40
    },
    "services": {
      "gateway": "healthy",
      "status_panel": "error_000",
      "health_api": "healthy",
      "dashboard": "error_000"
    },
    "network": {
      "connections": 7
    }
  },
  {
    "timestamp": "2026-03-07T13:42:47.928417",
    "system": {
      "load": {
        "1m": 2.16,
        "5m": 1.64,
        "15m": 1.58
      },
      "memory": {
        "total": 7266,
        "available": 4283,
        "used": 2983,
        "percent": 41.1
      },
      "gateway_processes": 42
    },
    "services": {
      "gateway": "healthy",
      "status_panel": "error_000",
      "health_api": "healthy",
      "dashboard": "error_000"
    },
    "network": {
      "connections": 9
    }
  },
  {
    "timestamp": "2026-03-07T13:47:50.059191",
    "system": {
      "load": {
        "1m": 1.31,
        "5m": 1.52,
        "15m": 1.56
      },
      "memory": {
        "total": 7266,
        "available": 4827,
        "used": 2439,
        "percent": 33.6
      },
      "gateway_processes": 40
    },
    "services": {
      "gateway": "healthy",
      "status_panel": "error_000",
      "health_api": "healthy",
      "dashboard": "error_000"
    },
    "network": {
      "connections": 7
    }
  },
  {
    "timestamp": "2026-03-07T13:52:51.519402",
    "system": {
      "load": {
        "1m": 1.72,
        "5m": 1.59,
        "15m": 1.58
      },
      "memory": {
        "total": 7266,
        "available": 4973,
        "used": 2293,
        "percent": 31.6
      },
      "gateway_processes": 40
    },
    "services": {
      "gateway": "healthy",
      "status_panel": "error_000",
      "health_api": "healthy",
      "dashboard": "error_000"
    },
    "network": {
      "connections": 7
    }
  },
  {
    "timestamp": "2026-03-07T13:57:53.540794",
    "system": {
      "load": {
        "1m": 1.53,
        "5m": 1.89,
        "15m": 1.74
      },
      "memory": {
        "total": 7266,
        "available": 4199,
        "used": 3067,
        "percent": 42.2
      },
      "gateway_processes": 43
    },
    "services": {
      "gateway": "healthy",
      "status_panel": "error_000",
      "health_api": "healthy",
      "dashboard": "error_000"
    },
    "network": {
      "connections": 8
    }
  },
  {
    "timestamp": "2026-03-07T14:02:55.188311",
    "system": {
      "load": {
        "1m": 1.26,
        "5m": 1.61,
        "15m": 1.67
      },
      "memory": {
        "total": 7266,
        "available": 4965,
        "used": 2301,
        "percent": 31.7
      },
      "gateway_processes": 40
    },
    "services": {
      "gateway": "healthy",
      "status_panel": "error_000",
      "health_api": "healthy",
      "dashboard": "error_000"
    },
    "network": {
      "connections": 7
    }
  },
  {
    "timestamp": "2026-03-07T14:07:57.371830",
    "system": {
      "load": {
        "1m": 1.65,
        "5m": 1.54,
        "15m": 1.61
      },
      "memory": {
        "total": 7266,
        "available": 4336,
        "used": 2930,
        "percent": 40.3
      },
      "gateway_processes": 40
    },
    "services": {
      "gateway": "healthy",
      "status_panel": "error_000",
      "health_api": "healthy",
      "dashboard": "error_000"
    },
    "network": {
      "connections": 7
    }
  },
  {
    "timestamp": "2026-03-07T14:12:59.241525",
    "system": {
      "load": {
        "1m": 1.22,
        "5m": 1.42,
        "15m": 1.54
      },
      "memory": {
        "total": 7266,
        "available": 4599,
        "used": 2667,
        "percent": 36.7
      },
      "gateway_processes": 40
    },
    "services": {
      "gateway": "healthy",
      "status_panel": "error_000",
      "health_api": "healthy",
      "dashboard": "error_000"
    },
    "network": {
      "connections": 9
    }
  },
  {
    "timestamp": "2026-03-07T14:18:01.544853",
    "system": {
      "load": {
        "1m": 1.88,
        "5m": 1.42,
        "15m": 1.48
      },
      "memory": {
        "total": 7266,
        "available": 4482,
        "used": 2784,
        "percent": 38.3
      },
      "gateway_processes": 40
    },
    "services": {
      "gateway": "healthy",
      "status_panel": "error_000",
      "health_api": "healthy",
      "dashboard": "error_000"
    },
    "network": {
      "connections": 7
    }
  },
  {
    "timestamp": "2026-03-07T14:23:03.655242",
    "system": {
      "load": {
        "1m": 1.6,
        "5m": 1.68,
        "15m": 1.59
      },
      "memory": {
        "total": 7266,
        "available": 4428,
        "used": 2838,
        "percent": 39.1
      },
      "gateway_processes": 43
    },
    "services": {
      "gateway": "healthy",
      "status_panel": "error_000",
      "health_api": "healthy",
      "dashboard": "error_000"
    },
    "network": {
      "connections": 7
    }
  },
  {
    "timestamp": "2026-03-07T14:28:06.132021",
    "system": {
      "load": {
        "1m": 1.67,
        "5m": 1.75,
        "15m": 1.64
      },
      "memory": {
        "total": 7266,
        "available": 4399,
        "used": 2867,
        "percent": 39.5
      },
      "gateway_processes": 40
    },
    "services": {
      "gateway": "healthy",
      "status_panel": "error_000",
      "health_api": "healthy",
      "dashboard": "error_000"
    },
    "network": {
      "connections": 9
    }
  },
  {
    "timestamp": "2026-03-07T14:33:07.827199",
    "system": {
      "load": {
        "1m": 0.73,
        "5m": 1.17,
        "15m": 1.42
      },
      "memory": {
        "total": 7266,
        "available": 4512,
        "used": 2754,
        "percent": 37.9
      },
      "gateway_processes": 40
    },
    "services": {
      "gateway": "healthy",
      "status_panel": "error_000",
      "health_api": "healthy",
      "dashboard": "error_000"
    },
    "network": {
      "connections": 5
    }
  },
  {
    "timestamp": "2026-03-07T14:38:09.631456",
    "system": {
      "load": {
        "1m": 0.69,
        "5m": 1.13,
        "15m": 1.36
      },
      "memory": {
        "total": 7266,
        "available": 5292,
        "used": 1974,
        "percent": 27.2
      },
      "gateway_processes": 40
    },
    "services": {
      "gateway": "healthy",
      "status_panel": "error_000",
      "health_api": "healthy",
      "dashboard": "error_000"
    },
    "network": {
      "connections": 5
    }
  },
  {
    "timestamp": "2026-03-07T14:43:11.240410",
    "system": {
      "load": {
        "1m": 1.17,
        "5m": 1.06,
        "15m": 1.25
      },
      "memory": {
        "total": 7266,
        "available": 4503,
        "used": 2763,
        "percent": 38.0
      },
      "gateway_processes": 40
    },
    "services": {
      "gateway": "healthy",
      "status_panel": "error_000",
      "health_api": "healthy",
      "dashboard": "error_000"
    },
    "network": {
      "connections": 6
    }
  },
  {
    "timestamp": "2026-03-07T14:48:13.083127",
    "system": {
      "load": {
        "1m": 1.36,
        "5m": 1.29,
        "15m": 1.29
      },
      "memory": {
        "total": 7266,
        "available": 5021,
        "used": 2245,
        "percent": 30.9
      },
      "gateway_processes": 40
    },
    "services": {
      "gateway": "healthy",
      "status_panel": "error_000",
      "health_api": "healthy",
      "dashboard": "error_000"
    },
    "network": {
      "connections": 6
    }
  },
  {
    "timestamp": "2026-03-07T14:53:14.838457",
    "system": {
      "load": {
        "1m": 0.83,
        "5m": 1.03,
        "15m": 1.17
      },
      "memory": {
        "total": 7266,
        "available": 5284,
        "used": 1982,
        "percent": 27.3
      },
      "gateway_processes": 40
    },
    "services": {
      "gateway": "healthy",
      "status_panel": "error_000",
      "health_api": "healthy",
      "dashboard": "error_000"
    },
    "network": {
      "connections": 8
    }
  },
  {
    "timestamp": "2026-03-07T14:58:16.549125",
    "system": {
      "load": {
        "1m": 1.26,
        "5m": 1.14,
        "15m": 1.17
      },
      "memory": {
        "total": 7266,
        "available": 4587,
        "used": 2679,
        "percent": 36.9
      },
      "gateway_processes": 40
    },
    "services": {
      "gateway": "healthy",
      "status_panel": "error_000",
      "health_api": "healthy",
      "dashboard": "error_000"
    },
    "network": {
      "connections": 6
    }
  },
  {
    "timestamp": "2026-03-07T15:03:18.418903",
    "system": {
      "load": {
        "1m": 1.13,
        "5m": 1.32,
        "15m": 1.24
      },
      "memory": {
        "total": 7266,
        "available": 4221,
        "used": 3045,
        "percent": 41.9
      },
      "gateway_processes": 43
    },
    "services": {
      "gateway": "healthy",
      "status_panel": "error_000",
      "health_api": "healthy",
      "dashboard": "error_000"
    },
    "network": {
      "connections": 5
    }
  },
  {
    "timestamp": "2026-03-07T15:08:20.043448",
    "system": {
      "load": {
        "1m": 2.97,
        "5m": 1.83,
        "15m": 1.44
      },
      "memory": {
        "total": 7266,
        "available": 4505,
        "used": 2761,
        "percent": 38.0
      },
      "gateway_processes": 40
    },
    "services": {
      "gateway": "healthy",
      "status_panel": "error_000",
      "health_api": "healthy",
      "dashboard": "error_000"
    },
    "network": {
      "connections": 9
    }
  },
  {
    "timestamp": "2026-03-07T15:13:21.650047",
    "system": {
      "load": {
        "1m": 1.16,
        "5m": 1.46,
        "15m": 1.37
      },
      "memory": {
        "total": 7266,
        "available": 5285,
        "used": 1981,
        "percent": 27.3
      },
      "gateway_processes": 40
    },
    "services": {
      "gateway": "healthy",
      "status_panel": "error_000",
      "health_api": "healthy",
      "dashboard": "error_000"
    },
    "network": {
      "connections": 5
    }
  },
  {
    "timestamp": "2026-03-07T15:18:23.539398",
    "system": {
      "load": {
        "1m": 1.49,
        "5m": 1.25,
        "15m": 1.29
      },
      "memory": {
        "total": 7266,
        "available": 4657,
        "used": 2609,
        "percent": 35.9
      },
      "gateway_processes": 40
    },
    "services": {
      "gateway": "healthy",
      "status_panel": "error_000",
      "health_api": "healthy",
      "dashboard": "error_000"
    },
    "network": {
      "connections": 7
    }
  },
  {
    "timestamp": "2026-03-07T15:23:25.513337",
    "system": {
      "load": {
        "1m": 1.24,
        "5m": 1.29,
        "15m": 1.3
      },
      "memory": {
        "total": 7266,
        "available": 4707,
        "used": 2559,
        "percent": 35.2
      },
      "gateway_processes": 43
    },
    "services": {
      "gateway": "healthy",
      "status_panel": "error_000",
      "health_api": "healthy",
      "dashboard": "error_000"
    },
    "network": {
      "connections": 10
    }
  },
  {
    "timestamp": "2026-03-07T15:28:28.576390",
    "system": {
      "load": {
        "1m": 1.41,
        "5m": 1.28,
        "15m": 1.28
      },
      "memory": {
        "total": 7266,
        "available": 4631,
        "used": 2635,
        "percent": 36.3
      },
      "gateway_processes": 43
    },
    "services": {
      "gateway": "healthy",
      "status_panel": "error_000",
      "health_api": "healthy",
      "dashboard": "error_000"
    },
    "network": {
      "connections": 10
    }
  },
  {
    "timestamp": "2026-03-07T15:33:30.420595",
    "system": {
      "load": {
        "1m": 1.29,
        "5m": 1.51,
        "15m": 1.4
      },
      "memory": {
        "total": 7266,
        "available": 4371,
        "used": 2895,
        "percent": 39.8
      },
      "gateway_processes": 40
    },
    "services": {
      "gateway": "healthy",
      "status_panel": "error_000",
      "health_api": "healthy",
      "dashboard": "error_000"
    },
    "network": {
      "connections": 6
    }
  },
  {
    "timestamp": "2026-03-07T15:38:31.927855",
    "system": {
      "load": {
        "1m": 1.38,
        "5m": 1.53,
        "15m": 1.44
      },
      "memory": {
        "total": 7266,
        "available": 5302,
        "used": 1964,
        "percent": 27.0
      },
      "gateway_processes": 40
    },
    "services": {
      "gateway": "healthy",
      "status_panel": "error_000",
      "health_api": "healthy",
      "dashboard": "error_000"
    },
    "network": {
      "connections": 7
    }
  },
  {
    "timestamp": "2026-03-07T15:43:33.642305",
    "system": {
      "load": {
        "1m": 0.97,
        "5m": 1.14,
        "15m": 1.3
      },
      "memory": {
        "total": 7266,
        "available": 5176,
        "used": 2090,
        "percent": 28.8
      },
      "gateway_processes": 43
    },
    "services": {
      "gateway": "healthy",
      "status_panel": "error_000",
      "health_api": "healthy",
      "dashboard": "error_000"
    },
    "network": {
      "connections": 6
    }
  },
  {
    "timestamp": "2026-03-07T15:48:35.582626",
    "system": {
      "load": {
        "1m": 1.33,
        "5m": 1.08,
        "15m": 1.21
      },
      "memory": {
        "total": 7266,
        "available": 4801,
        "used": 2465,
        "percent": 33.9
      },
      "gateway_processes": 43
    },
    "services": {
      "gateway": "healthy",
      "status_panel": "error_000",
      "health_api": "healthy",
      "dashboard": "error_000"
    },
    "network": {
      "connections": 5
    }
  },
  {
    "timestamp": "2026-03-07T15:53:37.192264",
    "system": {
      "load": {
        "1m": 1.49,
        "5m": 1.1,
        "15m": 1.16
      },
      "memory": {
        "total": 7266,
        "available": 4597,
        "used": 2669,
        "percent": 36.7
      },
      "gateway_processes": 40
    },
    "services": {
      "gateway": "healthy",
      "status_panel": "error_000",
      "health_api": "healthy",
      "dashboard": "error_000"
    },
    "network": {
      "connections": 7
    }
  },
  {
    "timestamp": "2026-03-07T15:58:39.168986",
    "system": {
      "load": {
        "1m": 1.95,
        "5m": 1.3,
        "15m": 1.2
      },
      "memory": {
        "total": 7266,
        "available": 4206,
        "used": 3060,
        "percent": 42.1
      },
      "gateway_processes": 40
    },
    "services": {
      "gateway": "healthy",
      "status_panel": "error_000",
      "health_api": "healthy",
      "dashboard": "error_000"
    },
    "network": {
      "connections": 6
    }
  },
  {
    "timestamp": "2026-03-07T16:03:40.983742",
    "system": {
      "load": {
        "1m": 0.72,
        "5m": 1.14,
        "15m": 1.17
      },
      "memory": {
        "total": 7266,
        "available": 4843,
        "used": 2423,
        "percent": 33.3
      },
      "gateway_processes": 41
    },
    "services": {
      "gateway": "healthy",
      "status_panel": "error_000",
      "health_api": "healthy",
      "dashboard": "error_000"
    },
    "network": {
      "connections": 8
    }
  },
  {
    "timestamp": "2026-03-07T16:08:42.501509",
    "system": {
      "load": {
        "1m": 0.88,
        "5m": 1.36,
        "15m": 1.3
      },
      "memory": {
        "total": 7266,
        "available": 5283,
        "used": 1983,
        "percent": 27.3
      },
      "gateway_processes": 40
    },
    "services": {
      "gateway": "healthy",
      "status_panel": "error_000",
      "health_api": "healthy",
      "dashboard": "error_000"
    },
    "network": {
      "connections": 5
    }
  },
  {
    "timestamp": "2026-03-07T16:13:44.387953",
    "system": {
      "load": {
        "1m": 1.33,
        "5m": 1.36,
        "15m": 1.31
      },
      "memory": {
        "total": 7266,
        "available": 4880,
        "used": 2386,
        "percent": 32.8
      },
      "gateway_processes": 42
    },
    "services": {
      "gateway": "healthy",
      "status_panel": "error_000",
      "health_api": "healthy",
      "dashboard": "error_000"
    },
    "network": {
      "connections": 8
    }
  },
  {
    "timestamp": "2026-03-07T16:18:46.411958",
    "system": {
      "load": {
        "1m": 1.01,
        "5m": 1.38,
        "15m": 1.35
      },
      "memory": {
        "total": 7266,
        "available": 4755,
        "used": 2511,
        "percent": 34.6
      },
      "gateway_processes": 40
    },
    "services": {
      "gateway": "healthy",
      "status_panel": "error_000",
      "health_api": "healthy",
      "dashboard": "error_000"
    },
    "network": {
      "connections": 8
    }
  },
  {
    "timestamp": "2026-03-07T16:23:48.527762",
    "system": {
      "load": {
        "1m": 1.64,
        "5m": 1.61,
        "15m": 1.46
      },
      "memory": {
        "total": 7266,
        "available": 3632,
        "used": 3634,
        "percent": 50.0
      },
      "gateway_processes": 45
    },
    "services": {
      "gateway": "healthy",
      "status_panel": "error_000",
      "health_api": "healthy",
      "dashboard": "error_000"
    },
    "network": {
      "connections": 7
    }
  },
  {
    "timestamp": "2026-03-07T16:28:50.223203",
    "system": {
      "load": {
        "1m": 1.81,
        "5m": 1.55,
        "15m": 1.45
      },
      "memory": {
        "total": 7266,
        "available": 4866,
        "used": 2400,
        "percent": 33.0
      },
      "gateway_processes": 40
    },
    "services": {
      "gateway": "healthy",
      "status_panel": "error_000",
      "health_api": "healthy",
      "dashboard": "error_000"
    },
    "network": {
      "connections": 6
    }
  },
  {
    "timestamp": "2026-03-07T16:33:52.912225",
    "system": {
      "load": {
        "1m": 0.5,
        "5m": 1.08,
        "15m": 1.29
      },
      "memory": {
        "total": 7266,
        "available": 4607,
        "used": 2659,
        "percent": 36.6
      },
      "gateway_processes": 40
    },
    "services": {
      "gateway": "healthy",
      "status_panel": "error_000",
      "health_api": "healthy",
      "dashboard": "error_000"
    },
    "network": {
      "connections": 8
    }
  },
  {
    "timestamp": "2026-03-07T16:38:54.492649",
    "system": {
      "load": {
        "1m": 0.87,
        "5m": 1.04,
        "15m": 1.22
      },
      "memory": {
        "total": 7266,
        "available": 5262,
        "used": 2004,
        "percent": 27.6
      },
      "gateway_processes": 40
    },
    "services": {
      "gateway": "healthy",
      "status_panel": "error_000",
      "health_api": "healthy",
      "dashboard": "error_000"
    },
    "network": {
      "connections": 7
    }
  },
  {
    "timestamp": "2026-03-07T16:43:56.151012",
    "system": {
      "load": {
        "1m": 1.55,
        "5m": 1.12,
        "15m": 1.19
      },
      "memory": {
        "total": 7266,
        "available": 4654,
        "used": 2612,
        "percent": 35.9
      },
      "gateway_processes": 43
    },
    "services": {
      "gateway": "healthy",
      "status_panel": "error_000",
      "health_api": "healthy",
      "dashboard": "error_000"
    },
    "network": {
      "connections": 7
    }
  },
  {
    "timestamp": "2026-03-07T16:48:57.843749",
    "system": {
      "load": {
        "1m": 1.08,
        "5m": 1.25,
        "15m": 1.23
      },
      "memory": {
        "total": 7266,
        "available": 5230,
        "used": 2036,
        "percent": 28.0
      },
      "gateway_processes": 40
    },
    "services": {
      "gateway": "healthy",
      "status_panel": "error_000",
      "health_api": "healthy",
      "dashboard": "error_000"
    },
    "network": {
      "connections": 7
    }
  },
  {
    "timestamp": "2026-03-07T16:53:59.734615",
    "system": {
      "load": {
        "1m": 0.94,
        "5m": 1.21,
        "15m": 1.22
      },
      "memory": {
        "total": 7266,
        "available": 5259,
        "used": 2007,
        "percent": 27.6
      },
      "gateway_processes": 40
    },
    "services": {
      "gateway": "healthy",
      "status_panel": "error_000",
      "health_api": "healthy",
      "dashboard": "error_000"
    },
    "network": {
      "connections": 5
    }
  },
  {
    "timestamp": "2026-03-07T16:59:01.566988",
    "system": {
      "load": {
        "1m": 1.42,
        "5m": 1.29,
        "15m": 1.24
      },
      "memory": {
        "total": 7266,
        "available": 4573,
        "used": 2693,
        "percent": 37.1
      },
      "gateway_processes": 40
    },
    "services": {
      "gateway": "healthy",
      "status_panel": "error_000",
      "health_api": "healthy",
      "dashboard": "error_000"
    },
    "network": {
      "connections": 8
    }
  },
  {
    "timestamp": "2026-03-07T17:04:04.062555",
    "system": {
      "load": {
        "1m": 1.22,
        "5m": 1.41,
        "15m": 1.3
      },
      "memory": {
        "total": 7266,
        "available": 4340,
        "used": 2926,
        "percent": 40.3
      },
      "gateway_processes": 43
    },
    "services": {
      "gateway": "healthy",
      "status_panel": "error_000",
      "health_api": "healthy",
      "dashboard": "error_000"
    },
    "network": {
      "connections": 10
    }
  },
  {
    "timestamp": "2026-03-07T17:09:06.228721",
    "system": {
      "load": {
        "1m": 0.94,
        "5m": 1.33,
        "15m": 1.32
      },
      "memory": {
        "total": 7266,
        "available": 5255,
        "used": 2011,
        "percent": 27.7
      },
      "gateway_processes": 40
    },
    "services": {
      "gateway": "healthy",
      "status_panel": "error_000",
      "health_api": "healthy",
      "dashboard": "error_000"
    },
    "network": {
      "connections": 6
    }
  },
  {
    "timestamp": "2026-03-07T17:14:08.067891",
    "system": {
      "load": {
        "1m": 1.49,
        "5m": 1.36,
        "15m": 1.32
      },
      "memory": {
        "total": 7266,
        "available": 4150,
        "used": 3116,
        "percent": 42.9
      },
      "gateway_processes": 43
    },
    "services": {
      "gateway": "healthy",
      "status_panel": "error_000",
      "health_api": "healthy",
      "dashboard": "error_000"
    },
    "network": {
      "connections": 6
    }
  },
  {
    "timestamp": "2026-03-07T17:19:09.711273",
    "system": {
      "load": {
        "1m": 1.1,
        "5m": 1.17,
        "15m": 1.24
      },
      "memory": {
        "total": 7266,
        "available": 4866,
        "used": 2400,
        "percent": 33.0
      },
      "gateway_processes": 40
    },
    "services": {
      "gateway": "healthy",
      "status_panel": "error_000",
      "health_api": "healthy",
      "dashboard": "error_000"
    },
    "network": {
      "connections": 5
    }
  },
  {
    "timestamp": "2026-03-07T17:24:11.237879",
    "system": {
      "load": {
        "1m": 1.62,
        "5m": 1.19,
        "15m": 1.22
      },
      "memory": {
        "total": 7266,
        "available": 4497,
        "used": 2769,
        "percent": 38.1
      },
      "gateway_processes": 40
    },
    "services": {
      "gateway": "healthy",
      "status_panel": "error_000",
      "health_api": "healthy",
      "dashboard": "error_000"
    },
    "network": {
      "connections": 7
    }
  },
  {
    "timestamp": "2026-03-07T17:29:13.838434",
    "system": {
      "load": {
        "1m": 3.02,
        "5m": 2.0,
        "15m": 1.52
      },
      "memory": {
        "total": 7266,
        "available": 4288,
        "used": 2978,
        "percent": 41.0
      },
      "gateway_processes": 43
    },
    "services": {
      "gateway": "healthy",
      "status_panel": "error_000",
      "health_api": "healthy",
      "dashboard": "error_000"
    },
    "network": {
      "connections": 8
    }
  },
  {
    "timestamp": "2026-03-07T17:34:16.159485",
    "system": {
      "load": {
        "1m": 4.25,
        "5m": 2.51,
        "15m": 1.81
      },
      "memory": {
        "total": 7266,
        "available": 4271,
        "used": 2995,
        "percent": 41.2
      },
      "gateway_processes": 45
    },
    "services": {
      "gateway": "healthy",
      "status_panel": "error_000",
      "health_api": "healthy",
      "dashboard": "error_000"
    },
    "network": {
      "connections": 9
    }
  },
  {
    "timestamp": "2026-03-07T17:39:18.282694",
    "system": {
      "load": {
        "1m": 1.08,
        "5m": 2.01,
        "15m": 1.84
      },
      "memory": {
        "total": 7266,
        "available": 4514,
        "used": 2752,
        "percent": 37.9
      },
      "gateway_processes": 43
    },
    "services": {
      "gateway": "healthy",
      "status_panel": "error_000",
      "health_api": "healthy",
      "dashboard": "error_000"
    },
    "network": {
      "connections": 6
    }
  },
  {
    "timestamp": "2026-03-07T17:44:19.966756",
    "system": {
      "load": {
        "1m": 1.3,
        "5m": 1.7,
        "15m": 1.77
      },
      "memory": {
        "total": 7266,
        "available": 4226,
        "used": 3040,
        "percent": 41.8
      },
      "gateway_processes": 43
    },
    "services": {
      "gateway": "healthy",
      "status_panel": "error_000",
      "health_api": "healthy",
      "dashboard": "error_000"
    },
    "network": {
      "connections": 7
    }
  },
  {
    "timestamp": "2026-03-07T17:49:21.924259",
    "system": {
      "load": {
        "1m": 0.89,
        "5m": 1.31,
        "15m": 1.58
      },
      "memory": {
        "total": 7266,
        "available": 4329,
        "used": 2937,
        "percent": 40.4
      },
      "gateway_processes": 40
    },
    "services": {
      "gateway": "healthy",
      "status_panel": "error_000",
      "health_api": "healthy",
      "dashboard": "error_000"
    },
    "network": {
      "connections": 5
    }
  },
  {
    "timestamp": "2026-03-07T17:54:23.675588",
    "system": {
      "load": {
        "1m": 1.79,
        "5m": 1.44,
        "15m": 1.55
      },
      "memory": {
        "total": 7266,
        "available": 4501,
        "used": 2765,
        "percent": 38.1
      },
      "gateway_processes": 40
    },
    "services": {
      "gateway": "healthy",
      "status_panel": "error_000",
      "health_api": "healthy",
      "dashboard": "error_000"
    },
    "network": {
      "connections": 6
    }
  },
  {
    "timestamp": "2026-03-07T17:59:25.891944",
    "system": {
      "load": {
        "1m": 0.89,
        "5m": 1.3,
        "15m": 1.45
      },
      "memory": {
        "total": 7266,
        "available": 5203,
        "used": 2063,
        "percent": 28.4
      },
      "gateway_processes": 40
    },
    "services": {
      "gateway": "healthy",
      "status_panel": "error_000",
      "health_api": "healthy",
      "dashboard": "error_000"
    },
    "network": {
      "connections": 6
    }
  },
  {
    "timestamp": "2026-03-07T18:04:27.460697",
    "system": {
      "load": {
        "1m": 0.58,
        "5m": 1.02,
        "15m": 1.31
      },
      "memory": {
        "total": 7266,
        "available": 4485,
        "used": 2781,
        "percent": 38.3
      },
      "gateway_processes": 40
    },
    "services": {
      "gateway": "healthy",
      "status_panel": "error_000",
      "health_api": "healthy",
      "dashboard": "error_000"
    },
    "network": {
      "connections": 5
    }
  },
  {
    "timestamp": "2026-03-07T18:09:29.139235",
    "system": {
      "load": {
        "1m": 1.18,
        "5m": 1.16,
        "15m": 1.28
      },
      "memory": {
        "total": 7266,
        "available": 4557,
        "used": 2709,
        "percent": 37.3
      },
      "gateway_processes": 42
    },
    "services": {
      "gateway": "healthy",
      "status_panel": "error_000",
      "health_api": "healthy",
      "dashboard": "error_000"
    },
    "network": {
      "connections": 7
    }
  },
  {
    "timestamp": "2026-03-07T18:14:30.709846",
    "system": {
      "load": {
        "1m": 1.19,
        "5m": 1.19,
        "15m": 1.26
      },
      "memory": {
        "total": 7266,
        "available": 4736,
        "used": 2530,
        "percent": 34.8
      },
      "gateway_processes": 40
    },
    "services": {
      "gateway": "healthy",
      "status_panel": "error_000",
      "health_api": "healthy",
      "dashboard": "error_000"
    },
    "network": {
      "connections": 5
    }
  },
  {
    "timestamp": "2026-03-07T18:19:32.353430",
    "system": {
      "load": {
        "1m": 0.41,
        "5m": 0.74,
        "15m": 1.05
      },
      "memory": {
        "total": 7266,
        "available": 5205,
        "used": 2061,
        "percent": 28.4
      },
      "gateway_processes": 40
    },
    "services": {
      "gateway": "healthy",
      "status_panel": "error_000",
      "health_api": "healthy",
      "dashboard": "error_000"
    },
    "network": {
      "connections": 6
    }
  },
  {
    "timestamp": "2026-03-07T18:24:33.973510",
    "system": {
      "load": {
        "1m": 2.14,
        "5m": 1.3,
        "15m": 1.17
      },
      "memory": {
        "total": 7266,
        "available": 4160,
        "used": 3106,
        "percent": 42.7
      },
      "gateway_processes": 40
    },
    "services": {
      "gateway": "healthy",
      "status_panel": "error_000",
      "health_api": "healthy",
      "dashboard": "error_000"
    },
    "network": {
      "connections": 9
    }
  },
  {
    "timestamp": "2026-03-07T18:29:35.745141",
    "system": {
      "load": {
        "1m": 1.16,
        "5m": 1.27,
        "15m": 1.19
      },
      "memory": {
        "total": 7266,
        "available": 5061,
        "used": 2205,
        "percent": 30.3
      },
      "gateway_processes": 43
    },
    "services": {
      "gateway": "healthy",
      "status_panel": "error_000",
      "health_api": "healthy",
      "dashboard": "error_000"
    },
    "network": {
      "connections": 5
    }
  },
  {
    "timestamp": "2026-03-07T18:34:37.429520",
    "system": {
      "load": {
        "1m": 1.18,
        "5m": 1.18,
        "15m": 1.18
      },
      "memory": {
        "total": 7266,
        "available": 4689,
        "used": 2577,
        "percent": 35.5
      },
      "gateway_processes": 40
    },
    "services": {
      "gateway": "healthy",
      "status_panel": "error_000",
      "health_api": "healthy",
      "dashboard": "error_000"
    },
    "network": {
      "connections": 7
    }
  }
]