[
  {
    "task": "metrics_collect",
    "status": "success",
    "timestamp": "2026-03-06T15:00:30.135498",
    "details": {
      "duration": 0.186848,
      "return_code": 0
    }
  },
  {
    "task": "api_health",
    "status": "success",
    "timestamp": "2026-03-06T15:00:30.261189",
    "details": {
      "duration": 0.123693,
      "return_code": 0
    }
  },
  {
    "task": "self_healer",
    "status": "success",
    "timestamp": "2026-03-06T15:01:00.466216",
    "details": {
      "duration": 0.173965,
      "return_code": 0
    }
  },
  {
    "task": "api_health",
    "status": "success",
    "timestamp": "2026-03-06T15:01:30.617008",
    "details": {
      "duration": 0.12086,
      "return_code": 0
    }
  },
  {
    "task": "api_health",
    "status": "success",
    "timestamp": "2026-03-06T15:02:30.803818",
    "details": {
      "duration": 0.129829,
      "return_code": 0
    }
  },
  {
    "task": "api_health",
    "status": "success",
    "timestamp": "2026-03-06T15:03:30.984989",
    "details": {
      "duration": 0.12047,
      "return_code": 0
    }
  },
  {
    "task": "api_health",
    "status": "success",
    "timestamp": "2026-03-06T15:04:31.158776",
    "details": {
      "duration": 0.116435,
      "return_code": 0
    }
  },
  {
    "task": "health_check",
    "status": "success",
    "timestamp": "2026-03-06T15:05:31.517358",
    "details": {
      "duration": 0.298444,
      "return_code": 0
    }
  },
  {
    "task": "metrics_collect",
    "status": "success",
    "timestamp": "2026-03-06T15:05:31.704322",
    "details": {
      "duration": 0.185281,
      "return_code": 0
    }
  },
  {
    "task": "api_health",
    "status": "success",
    "timestamp": "2026-03-06T15:05:31.818123",
    "details": {
      "duration": 0.111887,
      "return_code": 0
    }
  },
  {
    "task": "self_healer",
    "status": "success",
    "timestamp": "2026-03-06T15:06:01.954486",
    "details": {
      "duration": 0.094421,
      "return_code": 0
    }
  },
  {
    "task": "api_health",
    "status": "success",
    "timestamp": "2026-03-06T15:06:32.104019",
    "details": {
      "duration": 0.119833,
      "return_code": 0
    }
  },
  {
    "task": "api_health",
    "status": "success",
    "timestamp": "2026-03-06T15:07:32.293387",
    "details": {
      "duration": 0.121215,
      "return_code": 0
    }
  },
  {
    "task": "api_health",
    "status": "success",
    "timestamp": "2026-03-06T15:08:32.466271",
    "details": {
      "duration": 0.114835,
      "return_code": 0
    }
  },
  {
    "task": "api_health",
    "status": "success",
    "timestamp": "2026-03-06T15:09:32.666912",
    "details": {
      "duration": 0.138639,
      "return_code": 0
    }
  },
  {
    "task": "health_check",
    "status": "success",
    "timestamp": "2026-03-06T15:10:33.015593",
    "details": {
      "duration": 0.290737,
      "return_code": 0
    }
  },
  {
    "task": "metrics_collect",
    "status": "success",
    "timestamp": "2026-03-06T15:10:33.202727",
    "details": {
      "duration": 0.185114,
      "return_code": 0
    }
  },
  {
    "task": "api_health",
    "status": "success",
    "timestamp": "2026-03-06T15:10:33.322934",
    "details": {
      "duration": 0.118151,
      "return_code": 0
    }
  },
  {
    "task": "self_healer",
    "status": "success",
    "timestamp": "2026-03-06T15:11:03.442392",
    "details": {
      "duration": 0.091902,
      "return_code": 0
    }
  },
  {
    "task": "api_health",
    "status": "success",
    "timestamp": "2026-03-06T15:11:33.603636",
    "details": {
      "duration": 0.130358,
      "return_code": 0
    }
  },
  {
    "task": "api_health",
    "status": "success",
    "timestamp": "2026-03-06T15:12:33.810232",
    "details": {
      "duration": 0.144682,
      "return_code": 0
    }
  },
  {
    "task": "api_health",
    "status": "success",
    "timestamp": "2026-03-06T15:13:34.065186",
    "details": {
      "duration": 0.1827,
      "return_code": 0
    }
  },
  {
    "task": "api_health",
    "status": "success",
    "timestamp": "2026-03-06T15:14:34.245386",
    "details": {
      "duration": 0.115846,
      "return_code": 0
    }
  },
  {
    "task": "health_check",
    "status": "success",
    "timestamp": "2026-03-06T15:15:34.586929",
    "details": {
      "duration": 0.286663,
      "return_code": 0
    }
  },
  {
    "task": "metrics_collect",
    "status": "success",
    "timestamp": "2026-03-06T15:15:34.766997",
    "details": {
      "duration": 0.177918,
      "return_code": 0
    }
  },
  {
    "task": "api_health",
    "status": "success",
    "timestamp": "2026-03-06T15:15:34.895677",
    "details": {
      "duration": 0.126588,
      "return_code": 0
    }
  },
  {
    "task": "self_healer",
    "status": "success",
    "timestamp": "2026-03-06T15:16:05.043000",
    "details": {
      "duration": 0.121664,
      "return_code": 0
    }
  },
  {
    "task": "api_health",
    "status": "success",
    "timestamp": "2026-03-06T15:16:35.254062",
    "details": {
      "duration": 0.156425,
      "return_code": 0
    }
  },
  {
    "task": "api_health",
    "status": "success",
    "timestamp": "2026-03-06T15:17:35.439364",
    "details": {
      "duration": 0.126031,
      "return_code": 0
    }
  },
  {
    "task": "api_health",
    "status": "success",
    "timestamp": "2026-03-06T15:18:35.613891",
    "details": {
      "duration": 0.115222,
      "return_code": 0
    }
  },
  {
    "task": "api_health",
    "status": "success",
    "timestamp": "2026-03-06T15:19:35.785235",
    "details": {
      "duration": 0.112393,
      "return_code": 0
    }
  },
  {
    "task": "health_check",
    "status": "success",
    "timestamp": "2026-03-06T15:20:36.164659",
    "details": {
      "duration": 0.302426,
      "return_code": 0
    }
  },
  {
    "task": "metrics_collect",
    "status": "success",
    "timestamp": "2026-03-06T15:20:36.338635",
    "details": {
      "duration": 0.171691,
      "return_code": 0
    }
  },
  {
    "task": "api_health",
    "status": "success",
    "timestamp": "2026-03-06T15:20:36.457375",
    "details": {
      "duration": 0.116948,
      "return_code": 0
    }
  },
  {
    "task": "self_healer",
    "status": "success",
    "timestamp": "2026-03-06T15:21:06.633269",
    "details": {
      "duration": 0.147238,
      "return_code": 0
    }
  },
  {
    "task": "api_health",
    "status": "success",
    "timestamp": "2026-03-06T15:21:36.772289",
    "details": {
      "duration": 0.108959,
      "return_code": 0
    }
  },
  {
    "task": "api_health",
    "status": "success",
    "timestamp": "2026-03-06T15:22:36.937226",
    "details": {
      "duration": 0.115979,
      "return_code": 0
    }
  },
  {
    "task": "api_health",
    "status": "success",
    "timestamp": "2026-03-06T15:23:37.125190",
    "details": {
      "duration": 0.128901,
      "return_code": 0
    }
  },
  {
    "task": "api_health",
    "status": "success",
    "timestamp": "2026-03-06T15:24:37.295504",
    "details": {
      "duration": 0.11028,
      "return_code": 0
    }
  },
  {
    "task": "health_check",
    "status": "success",
    "timestamp": "2026-03-06T15:25:37.643756",
    "details": {
      "duration": 0.291136,
      "return_code": 0
    }
  },
  {
    "task": "metrics_collect",
    "status": "success",
    "timestamp": "2026-03-06T15:25:37.823433",
    "details": {
      "duration": 0.177509,
      "return_code": 0
    }
  },
  {
    "task": "api_health",
    "status": "success",
    "timestamp": "2026-03-06T15:25:37.942669",
    "details": {
      "duration": 0.117214,
      "return_code": 0
    }
  },
  {
    "task": "self_healer",
    "status": "success",
    "timestamp": "2026-03-06T15:26:08.058785",
    "details": {
      "duration": 0.085116,
      "return_code": 0
    }
  },
  {
    "task": "api_health",
    "status": "success",
    "timestamp": "2026-03-06T15:26:38.202934",
    "details": {
      "duration": 0.114761,
      "return_code": 0
    }
  },
  {
    "task": "api_health",
    "status": "success",
    "timestamp": "2026-03-06T15:27:38.372226",
    "details": {
      "duration": 0.1137,
      "return_code": 0
    }
  },
  {
    "task": "api_health",
    "status": "success",
    "timestamp": "2026-03-06T15:28:38.547465",
    "details": {
      "duration": 0.121535,
      "return_code": 0
    }
  },
  {
    "task": "api_health",
    "status": "success",
    "timestamp": "2026-03-06T15:29:38.718966",
    "details": {
      "duration": 0.118061,
      "return_code": 0
    }
  },
  {
    "task": "health_check",
    "status": "success",
    "timestamp": "2026-03-06T15:30:39.078466",
    "details": {
      "duration": 0.289923,
      "return_code": 0
    }
  },
  {
    "task": "metrics_collect",
    "status": "success",
    "timestamp": "2026-03-06T15:30:39.256896",
    "details": {
      "duration": 0.176129,
      "return_code": 0
    }
  },
  {
    "task": "api_health",
    "status": "success",
    "timestamp": "2026-03-06T15:30:39.369032",
    "details": {
      "duration": 0.110387,
      "return_code": 0
    }
  },
  {
    "task": "self_healer",
    "status": "success",
    "timestamp": "2026-03-06T15:31:09.486427",
    "details": {
      "duration": 0.089128,
      "return_code": 0
    }
  },
  {
    "task": "api_health",
    "status": "success",
    "timestamp": "2026-03-06T15:31:39.644481",
    "details": {
      "duration": 0.11498,
      "return_code": 0
    }
  },
  {
    "task": "api_health",
    "status": "success",
    "timestamp": "2026-03-06T15:32:39.819448",
    "details": {
      "duration": 0.117622,
      "return_code": 0
    }
  },
  {
    "task": "api_health",
    "status": "success",
    "timestamp": "2026-03-06T15:33:39.988480",
    "details": {
      "duration": 0.113887,
      "return_code": 0
    }
  },
  {
    "task": "api_health",
    "status": "success",
    "timestamp": "2026-03-06T15:34:40.175824",
    "details": {
      "duration": 0.12009,
      "return_code": 0
    }
  },
  {
    "task": "health_check",
    "status": "success",
    "timestamp": "2026-03-06T15:35:40.582450",
    "details": {
      "duration": 0.346655,
      "return_code": 0
    }
  },
  {
    "task": "metrics_collect",
    "status": "success",
    "timestamp": "2026-03-06T15:35:40.831894",
    "details": {
      "duration": 0.246347,
      "return_code": 0
    }
  },
  {
    "task": "api_health",
    "status": "success",
    "timestamp": "2026-03-06T15:35:40.975812",
    "details": {
      "duration": 0.141818,
      "return_code": 0
    }
  },
  {
    "task": "self_healer",
    "status": "success",
    "timestamp": "2026-03-06T15:36:11.095217",
    "details": {
      "duration": 0.088465,
      "return_code": 0
    }
  },
  {
    "task": "api_health",
    "status": "success",
    "timestamp": "2026-03-06T15:36:41.301984",
    "details": {
      "duration": 0.178587,
      "return_code": 0
    }
  },
  {
    "task": "api_health",
    "status": "success",
    "timestamp": "2026-03-06T15:37:41.479675",
    "details": {
      "duration": 0.119068,
      "return_code": 0
    }
  },
  {
    "task": "api_health",
    "status": "success",
    "timestamp": "2026-03-06T15:38:41.655849",
    "details": {
      "duration": 0.119154,
      "return_code": 0
    }
  },
  {
    "task": "api_health",
    "status": "success",
    "timestamp": "2026-03-06T15:39:41.902688",
    "details": {
      "duration": 0.189592,
      "return_code": 0
    }
  },
  {
    "task": "health_check",
    "status": "success",
    "timestamp": "2026-03-06T15:40:42.254764",
    "details": {
      "duration": 0.293508,
      "return_code": 0
    }
  },
  {
    "task": "metrics_collect",
    "status": "success",
    "timestamp": "2026-03-06T15:40:42.428652",
    "details": {
      "duration": 0.171639,
      "return_code": 0
    }
  },
  {
    "task": "api_health",
    "status": "success",
    "timestamp": "2026-03-06T15:40:42.541252",
    "details": {
      "duration": 0.110464,
      "return_code": 0
    }
  },
  {
    "task": "self_healer",
    "status": "success",
    "timestamp": "2026-03-06T15:41:12.656019",
    "details": {
      "duration": 0.084713,
      "return_code": 0
    }
  },
  {
    "task": "api_health",
    "status": "success",
    "timestamp": "2026-03-06T15:41:42.801264",
    "details": {
      "duration": 0.116266,
      "return_code": 0
    }
  },
  {
    "task": "api_health",
    "status": "success",
    "timestamp": "2026-03-06T15:42:42.969764",
    "details": {
      "duration": 0.111652,
      "return_code": 0
    }
  },
  {
    "task": "api_health",
    "status": "success",
    "timestamp": "2026-03-06T15:43:43.161175",
    "details": {
      "duration": 0.122677,
      "return_code": 0
    }
  },
  {
    "task": "api_health",
    "status": "success",
    "timestamp": "2026-03-06T15:44:43.335734",
    "details": {
      "duration": 0.118484,
      "return_code": 0
    }
  },
  {
    "task": "health_check",
    "status": "success",
    "timestamp": "2026-03-06T15:45:43.706690",
    "details": {
      "duration": 0.308759,
      "return_code": 0
    }
  },
  {
    "task": "metrics_collect",
    "status": "success",
    "timestamp": "2026-03-06T15:45:43.889145",
    "details": {
      "duration": 0.180595,
      "return_code": 0
    }
  },
  {
    "task": "api_health",
    "status": "success",
    "timestamp": "2026-03-06T15:45:44.006176",
    "details": {
      "duration": 0.115076,
      "return_code": 0
    }
  },
  {
    "task": "self_healer",
    "status": "success",
    "timestamp": "2026-03-06T15:46:14.198575",
    "details": {
      "duration": 0.165082,
      "return_code": 0
    }
  },
  {
    "task": "api_health",
    "status": "success",
    "timestamp": "2026-03-06T15:46:44.346780",
    "details": {
      "duration": 0.117315,
      "return_code": 0
    }
  },
  {
    "task": "api_health",
    "status": "success",
    "timestamp": "2026-03-06T15:47:44.570080",
    "details": {
      "duration": 0.169763,
      "return_code": 0
    }
  },
  {
    "task": "api_health",
    "status": "success",
    "timestamp": "2026-03-06T15:48:44.760029",
    "details": {
      "duration": 0.124935,
      "return_code": 0
    }
  },
  {
    "task": "api_health",
    "status": "success",
    "timestamp": "2026-03-06T15:49:44.940295",
    "details": {
      "duration": 0.121992,
      "return_code": 0
    }
  },
  {
    "task": "health_check",
    "status": "success",
    "timestamp": "2026-03-06T15:50:45.374809",
    "details": {
      "duration": 0.380161,
      "return_code": 0
    }
  },
  {
    "task": "metrics_collect",
    "status": "success",
    "timestamp": "2026-03-06T15:50:45.546933",
    "details": {
      "duration": 0.170009,
      "return_code": 0
    }
  },
  {
    "task": "api_health",
    "status": "success",
    "timestamp": "2026-03-06T15:50:45.661603",
    "details": {
      "duration": 0.112485,
      "return_code": 0
    }
  },
  {
    "task": "self_healer",
    "status": "success",
    "timestamp": "2026-03-06T15:51:15.792162",
    "details": {
      "duration": 0.100006,
      "return_code": 0
    }
  },
  {
    "task": "api_health",
    "status": "success",
    "timestamp": "2026-03-06T15:51:45.935831",
    "details": {
      "duration": 0.115063,
      "return_code": 0
    }
  },
  {
    "task": "api_health",
    "status": "success",
    "timestamp": "2026-03-06T15:52:46.109303",
    "details": {
      "duration": 0.115605,
      "return_code": 0
    }
  },
  {
    "task": "api_health",
    "status": "success",
    "timestamp": "2026-03-06T15:53:46.276262",
    "details": {
      "duration": 0.112051,
      "return_code": 0
    }
  },
  {
    "task": "api_health",
    "status": "success",
    "timestamp": "2026-03-06T15:54:46.457537",
    "details": {
      "duration": 0.124434,
      "return_code": 0
    }
  },
  {
    "task": "health_check",
    "status": "success",
    "timestamp": "2026-03-06T15:55:46.806187",
    "details": {
      "duration": 0.286248,
      "return_code": 0
    }
  },
  {
    "task": "metrics_collect",
    "status": "success",
    "timestamp": "2026-03-06T15:55:47.030185",
    "details": {
      "duration": 0.221784,
      "return_code": 0
    }
  },
  {
    "task": "api_health",
    "status": "success",
    "timestamp": "2026-03-06T15:55:47.169657",
    "details": {
      "duration": 0.134533,
      "return_code": 0
    }
  },
  {
    "task": "self_healer",
    "status": "success",
    "timestamp": "2026-03-06T15:56:17.286959",
    "details": {
      "duration": 0.086449,
      "return_code": 0
    }
  },
  {
    "task": "api_health",
    "status": "success",
    "timestamp": "2026-03-06T15:56:47.449433",
    "details": {
      "duration": 0.126297,
      "return_code": 0
    }
  },
  {
    "task": "api_health",
    "status": "success",
    "timestamp": "2026-03-06T15:57:47.633311",
    "details": {
      "duration": 0.116722,
      "return_code": 0
    }
  },
  {
    "task": "api_health",
    "status": "success",
    "timestamp": "2026-03-06T15:58:47.801392",
    "details": {
      "duration": 0.1138,
      "return_code": 0
    }
  },
  {
    "task": "api_health",
    "status": "success",
    "timestamp": "2026-03-06T15:59:48.037037",
    "details": {
      "duration": 0.176815,
      "return_code": 0
    }
  },
  {
    "task": "health_check",
    "status": "success",
    "timestamp": "2026-03-06T16:00:48.396371",
    "details": {
      "duration": 0.30454,
      "return_code": 0
    }
  },
  {
    "task": "metrics_collect",
    "status": "success",
    "timestamp": "2026-03-06T16:00:48.580992",
    "details": {
      "duration": 0.182234,
      "return_code": 0
    }
  },
  {
    "task": "api_health",
    "status": "success",
    "timestamp": "2026-03-06T16:00:48.700629",
    "details": {
      "duration": 0.117788,
      "return_code": 0
    }
  },
  {
    "task": "self_healer",
    "status": "success",
    "timestamp": "2026-03-06T16:01:18.848844",
    "details": {
      "duration": 0.101177,
      "return_code": 0
    }
  },
  {
    "task": "api_health",
    "status": "success",
    "timestamp": "2026-03-06T16:01:48.993403",
    "details": {
      "duration": 0.116567,
      "return_code": 0
    }
  }
]