{
  "tasks": {
    "test": {
      "status": "active"
    },
    "health_check": {
      "last_run": "2026-03-08T12:07:36.795777",
      "success": true,
      "duration": 0.443578
    },
    "metrics_collect": {
      "last_run": "2026-03-08T12:07:37.000012",
      "success": true,
      "duration": 0.198013
    },
    "api_health": {
      "last_run": "2026-03-08T12:07:37.127929",
      "success": true,
      "duration": 0.125284
    },
    "self_healer": {
      "last_run": "2026-03-08T12:08:07.285511",
      "success": true,
      "duration": 0.127215
    }
  },
  "last_save": "2026-03-06T11:34:27.897847",
  "start_time": "2026-03-06T14:30:13.685600",
  "last_check": "2026-03-08T12:08:07.287656",
  "recovered_at": "2026-03-06T12:48:58.998650",
  "crash_recovery": true
}