{
  "evolution_history": [
    {
      "cycle_id": 1,
      "started_at": "2026-03-05T05:51:46.995616",
      "steps": [
        {
          "step": "self_discovery",
          "status": "executed",
          "timestamp": "2026-03-05T05:51:46.995646",
          "details": {
            "timestamp": "2026-03-05T05:51:46.995649",
            "systems_count": 70,
            "total_capabilities": [
              "automation",
              "learning",
              "analysis",
              "prediction",
              "optimization"
            ],
            "performance_metrics": {},
            "improvement_areas": [
              "cross_system_integration",
              "real_time_adaptation",
              "predictive_capabilities",
              "resource_optimization"
            ]
          },
          "outcome": "\u53d1\u73b070\u4e2a\u7cfb\u7edf\uff0c\u5177\u59075\u79cd\u80fd\u529b"
        },
        {
          "step": "improvement_discovery",
          "status": "executed",
          "timestamp": "2026-03-05T05:51:47.018571",
          "details": {
            "improvements_found": 37
          },
          "outcome": "\u53d1\u73b037\u4e2a\u6539\u8fdb\u673a\u4f1a"
        },
        {
          "step": "plan_generation",
          "status": "executed",
          "timestamp": "2026-03-05T05:51:47.038397",
          "details": {
            "name": "autonomous-evolution-cycle",
            "created_at": "2026-03-05T05:51:47.061158",
            "phases": [
              {
                "phase": 1,
                "name": "\u80fd\u529b\u589e\u5f3a",
                "actions": [
                  "\u5f3a\u5316\u73b0\u6709\u4f18\u5316\u7b97\u6cd5",
                  "\u6269\u5c55\u5b66\u4e60\u80fd\u529b",
                  "\u63d0\u5347\u9884\u6d4b\u7cbe\u5ea6"
                ]
              },
              {
                "phase": 2,
                "name": "\u7cfb\u7edf\u6574\u5408",
                "actions": [
                  "\u8de8\u6a21\u5757\u534f\u4f5c\u4f18\u5316",
                  "\u8d44\u6e90\u5171\u4eab\u4e0e\u590d\u7528",
                  "\u63a5\u53e3\u6807\u51c6\u5316"
                ]
              },
              {
                "phase": 3,
                "name": "\u81ea\u6211\u8d85\u8d8a",
                "actions": [
                  "\u7a81\u7834\u73b0\u6709\u80fd\u529b\u8fb9\u754c",
                  "\u63a2\u7d22\u65b0\u8303\u5f0f",
                  "\u5b9e\u73b0\u66f4\u9ad8\u5c42\u6b21\u7684\u62bd\u8c61"
                ]
              }
            ],
            "expected_outcomes": [
              "\u7cfb\u7edf\u54cd\u5e94\u901f\u5ea6\u63d0\u534720%",
              "\u5b66\u4e60\u6548\u7387\u63d0\u534730%",
              "\u8de8\u57df\u80fd\u529b\u589e\u5f3a50%"
            ]
          },
          "outcome": "\u751f\u6210\u5305\u542b3\u4e2a\u9636\u6bb5\u7684\u8fdb\u5316\u8ba1\u5212"
        },
        {
          "step": "execution",
          "status": "executed",
          "timestamp": "2026-03-05T05:51:47.061235",
          "details": {},
          "outcome": "\u6267\u884c\u8fdb\u5316\u6b65\u9aa4 - \u80fd\u529b\u5df2\u589e\u5f3a"
        },
        {
          "step": "evaluation",
          "status": "executed",
          "timestamp": "2026-03-05T05:51:47.061242",
          "details": {},
          "outcome": "\u8fdb\u5316\u6548\u679c\u8bc4\u4f30\u5b8c\u6210"
        }
      ],
      "completed_at": "2026-03-05T05:51:47.061246",
      "status": "completed"
    }
  ],
  "last_update": "2026-03-05T05:51:47.061251"
}